MANIFEST.in
README.md
debian_dependencies.txt
requirements.txt
requirements_build.txt
requirements_dev.txt
setup.py
version.txt
apimas/__init__.py
apimas/drf/__init__.py
apimas/drf/django_rest.py
apimas/drf/mixins.py
apimas/drf/permissions.py
apimas/drf/serializers.py
apimas/drf/utils.py
apimas/drf/views.py
apimas/drf/viewsets.py
apimas/drf/testing/__init__.py
apimas/drf/testing/testing.py
apimas/drf/testing/utils.py
apimas_drf.egg-info/PKG-INFO
apimas_drf.egg-info/SOURCES.txt
apimas_drf.egg-info/dependency_links.txt
apimas_drf.egg-info/namespace_packages.txt
apimas_drf.egg-info/requires.txt
apimas_drf.egg-info/top_level.txt
tests/functional/__init__.py
tests/functional/test_crud.py
tests/functional/test_hooks.py
tests/functional/test_nested.py
tests/functional/test_non_model.py